{
    "family": "reserve-app",
    "networkMode": "bridge",
    "requiresCompatibilities": ["EC2"],
    "executionRoleArn": "arn:aws:iam::334689162817:role/ecsTaskExecutionRole",
    "containerDefinitions": [
        {
            "name": "postgres",
            "image": "postgres:15-alpine",
            "essential": true,
            "memory": 256,
            "environment": [
                {"name": "POSTGRES_DB", "value": "central_reserve"},
                {"name": "POSTGRES_USER", "value": "postgres"},
                {"name": "POSTGRES_PASSWORD", "value": "postgres123"}
            ],
            "portMappings": [
                {
                    "containerPort": 5432,
                    "hostPort": 5432,
                    "protocol": "tcp"
                }
            ],
            "healthCheck": {
                "command": ["CMD-SHELL", "pg_isready -U postgres -d central_reserve"],
                "interval": 30,
                "timeout": 5,
                "retries": 3,
                "startPeriod": 60
            },
            "logConfiguration": {
                "logDriver": "awslogs",
                "options": {
                    "awslogs-group": "/ecs/reserve-app",
                    "awslogs-region": "us-east-1",
                    "awslogs-stream-prefix": "postgres"
                }
            }
        },
        {
            "name": "backend",
            "image": "public.ecr.aws/d3a6d4r1/cam/reserve:backend-latest",
            "essential": true,
            "memory": 512,
            "environment": [
                {"name": "DB_HOST", "value": "postgres"},
                {"name": "DB_PORT", "value": "5432"},
                {"name": "DB_NAME", "value": "central_reserve"},
                {"name": "DB_USER", "value": "postgres"},
                {"name": "DB_PASS", "value": "postgres123"},
                {"name": "DB_LOG_LEVEL", "value": "info"},
                {"name": "PGSSLMODE", "value": "disable"},
                {"name": "APP_ENV", "value": "production"},
                {"name": "HTTP_PORT", "value": "3050"},
                {"name": "LOG_LEVEL", "value": "info"},
                {"name": "JWT_SECRET", "value": "your-secret-key-here"},
                {"name": "URL_BASE_SWAGGER", "value": "/swagger/"}
            ],
            "portMappings": [
                {
                    "containerPort": 3050,
                    "hostPort": 3050,
                    "protocol": "tcp"
                }
            ],
            "links": ["postgres"],
            "dependsOn": [
                {
                    "containerName": "postgres",
                    "condition": "HEALTHY"
                }
            ],
            "healthCheck": {
                "command": ["CMD-SHELL", "ps aux | grep '[c]entral_reserve' || exit 1"],
                "interval": 30,
                "timeout": 5,
                "retries": 3,
                "startPeriod": 60
            },
            "logConfiguration": {
                "logDriver": "awslogs",
                "options": {
                    "awslogs-group": "/ecs/reserve-app",
                    "awslogs-region": "us-east-1",
                    "awslogs-stream-prefix": "backend"
                }
            }
        },
                 {
             "name": "migrator",
             "image": "public.ecr.aws/d3a6d4r1/cam/reserve:migrator-latest",
             "essential": false,
             "memory": 128,
             "environment": [
                 {"name": "DB_HOST", "value": "postgres"},
                 {"name": "DB_PORT", "value": "5432"},
                 {"name": "DB_NAME", "value": "central_reserve"},
                 {"name": "DB_USER", "value": "postgres"},
                 {"name": "DB_PASS", "value": "postgres123"},
                 {"name": "DB_LOG_LEVEL", "value": "info"},
                 {"name": "PGSSLMODE", "value": "disable"},
                 {"name": "APP_ENV", "value": "production"},
                 {"name": "HTTP_PORT", "value": "8080"},
                 {"name": "LOG_LEVEL", "value": "info"},
                 {"name": "JWT_SECRET", "value": "your-secret-key-here"}
             ],
             "links": ["postgres"],
             "dependsOn": [
                 {
                     "containerName": "postgres",
                     "condition": "HEALTHY"
                 }
             ],
             "logConfiguration": {
                 "logDriver": "awslogs",
                 "options": {
                     "awslogs-group": "/ecs/reserve-app",
                     "awslogs-region": "us-east-1",
                     "awslogs-stream-prefix": "migrator"
                 }
             }
         },
         {
             "name": "frontend", 
             "image": "public.ecr.aws/d3a6d4r1/cam/reserve:frontend-latest",
             "essential": true,
             "memory": 128,
             "environment": [
                 {"name": "REACT_APP_API_BASE_URL", "value": "http://54.81.48.34:3050"},
                 {"name": "REACT_APP_NAME", "value": "Reserve App"},
                 {"name": "REACT_APP_VERSION", "value": "1.0.0"},
                 {"name": "NODE_ENV", "value": "production"}
             ],
             "portMappings": [
                 {
                     "containerPort": 80,
                     "hostPort": 80,
                     "protocol": "tcp"
                 }
             ],
             "links": ["backend"],
             "dependsOn": [
                 {
                     "containerName": "backend",
                     "condition": "HEALTHY"
                 }
             ],
             "logConfiguration": {
                 "logDriver": "awslogs",
                 "options": {
                     "awslogs-group": "/ecs/reserve-app",
                     "awslogs-region": "us-east-1",
                     "awslogs-stream-prefix": "frontend"
                 }
             }
         }
    ]
}
